{
  "phase": 703,
  "file": "REN27/542238759-542238759.html",
  "file_id": "30b2ede66f",
  "source_items": 593,
  "translation_rows": 593,
  "source_items_match_translation_rows": true,
  "duplicate_rows": [],
  "missing_item_ids": [],
  "extra_item_ids": [],
  "tag_fingerprint_identical": true,
  "rendered_markup_matches_target_markup": true,
  "glossary_violations": [],
  "direct_placement_missing": [],
  "actionable_long_source_residuals": [],
  "accepted_long_source_residuals": [
    {
      "item_id": "30b2ede66f:90",
      "source": "XPU Features and Limitations"
    },
    {
      "item_id": "30b2ede66f:110",
      "source": "Image Outputs and Displays"
    },
    {
      "item_id": "30b2ede66f:127",
      "source": "https://openexr.com/en/latest/DeepIDsSpecification.html"
    },
    {
      "item_id": "30b2ede66f:232",
      "source": "XPU Features and Limitations"
    },
    {
      "item_id": "30b2ede66f:264",
      "source": "Glass and glass single scattering"
    },
    {
      "item_id": "30b2ede66f:302",
      "source": "Image Outputs and Displays"
    },
    {
      "item_id": "30b2ede66f:385",
      "source": "Image Outputs and Displays"
    },
    {
      "item_id": "30b2ede66f:493",
      "source": "RenderMan for Blender"
    },
    {
      "item_id": "30b2ede66f:524",
      "source": "RenderMan for Maya"
    },
    {
      "item_id": "30b2ede66f:534",
      "source": "RenderMan for Katana"
    },
    {
      "item_id": "30b2ede66f:544",
      "source": "RenderMan for Houdini"
    }
  ],
  "actionable_ascii_heavy_residuals": [],
  "accepted_ascii_heavy_residuals": [
    {
      "item_id": "30b2ede66f:0",
      "text": "欢迎使用 RenderMan 27.0",
      "ascii_letters": 9,
      "cjk_chars": 4
    },
    {
      "item_id": "30b2ede66f:13",
      "text": "Stylized Looks",
      "ascii_letters": 13,
      "cjk_chars": 0
    },
    {
      "item_id": "30b2ede66f:19",
      "text": "MaterialX Lama",
      "ascii_letters": 13,
      "cjk_chars": 0
    },
    {
      "item_id": "30b2ede66f:30",
      "text": "Apple Silicon",
      "ascii_letters": 12,
      "cjk_chars": 0
    },
    {
      "item_id": "30b2ede66f:33",
      "text": "符合 VFX Reference Platform 2024",
      "ascii_letters": 20,
      "cjk_chars": 2
    },
    {
      "item_id": "30b2ede66f:41",
      "text": "Texture Manager 现在默认使用 OpenImageIO",
      "ascii_letters": 25,
      "cjk_chars": 6
    },
    {
      "item_id": "30b2ede66f:43",
      "text": "从 txmake 切换到 OpenImageIO",
      "ascii_letters": 17,
      "cjk_chars": 4
    },
    {
      "item_id": "30b2ede66f:58",
      "text": "新的 OSL trace 能力",
      "ascii_letters": 8,
      "cjk_chars": 4
    },
    {
      "item_id": "30b2ede66f:67",
      "text": "XPU 中的 Light filters（灯光过滤器）",
      "ascii_letters": 15,
      "cjk_chars": 7
    },
    {
      "item_id": "30b2ede66f:69",
      "text": "PxrPathTracer 增强",
      "ascii_letters": 13,
      "cjk_chars": 2
    },
    {
      "item_id": "30b2ede66f:70",
      "text": "，包括对 clampDepth 和 clampLuminance 参数的支持。",
      "ascii_letters": 24,
      "cjk_chars": 9
    },
    {
      "item_id": "30b2ede66f:72",
      "text": "XPU 中的 Deep OpenEXR 支持",
      "ascii_letters": 14,
      "cjk_chars": 4
    },
    {
      "item_id": "30b2ede66f:76",
      "text": "Matte object（遮罩对象）支持和 holdout 工作流",
      "ascii_letters": 18,
      "cjk_chars": 10
    },
    {
      "item_id": "30b2ede66f:98",
      "text": "为 XPU 中的异步 exitAt 和 checkpoint interval（检查点间隔）添加了支持。RMAN-22620",
      "ascii_letters": 31,
      "cjk_chars": 16
    },
    {
      "item_id": "30b2ede66f:105",
      "text": "Attribute \"shade\" \"relativepixelvariance\" 和 \"minsamples\" 现在已在 XPU 中实现。RMAN-22492",
      "ascii_letters": 52,
      "cjk_chars": 8
    },
    {
      "item_id": "30b2ede66f:111",
      "text": "XPU 现在完整支持 display filters（显示过滤器）。通过 OSL 可使用等价于 Read、ReadRegion 和 Write 的 API：",
      "ascii_letters": 42,
      "cjk_chars": 21
    },
    {
      "item_id": "30b2ede66f:114",
      "text": "ReadRegion 等价项：",
      "ascii_letters": 10,
      "cjk_chars": 3
    },
    {
      "item_id": "30b2ede66f:118",
      "text": "XPU 部分支持 sample filters（采样过滤器）。Read 和 Write 受支持，而来自 sample filters 的 ReadRegion、primvar 访问和 trace() 尚不受支持。",
      "ascii_letters": 60,
      "cjk_chars": 25
    },
    {
      "item_id": "30b2ede66f:119",
      "text": "XPU 完整支持连接到 sample filters 和 display filters 的 OSL patterns。RMAN-19911",
      "ascii_letters": 45,
      "cjk_chars": 9
    },
    {
      "item_id": "30b2ede66f:122",
      "text": "RenderMan XPU 现在完整支持 OpenEXR Deep IDs，包括自动生成 OpenEXR 3.0 风格 ID 清单的能力，其 metadata 类型为 \"CompressedIDManifest\"，用于 model ids。若要使用此功能，必须向渲染器提供以下内容：",
      "ascii_letters": 71,
      "cjk_chars": 44
    },
    {
      "item_id": "30b2ede66f:123",
      "text": "必须将名为 \"int id\" 和 \"int id2\" 的两个 display channels 传递给 deep display driver；",
      "ascii_letters": 42,
      "cjk_chars": 12
    },
    {
      "item_id": "30b2ede66f:124",
      "text": "几何实例必须具有 Attribute \"identifier\" \"string name\"、\"int id\" 和 \"int id2\"",
      "ascii_letters": 39,
      "cjk_chars": 9
    },
    {
      "item_id": "30b2ede66f:127",
      "text": "https://openexr.com/en/latest/DeepIDsSpecification.html",
      "ascii_letters": 47,
      "cjk_chars": 0
    },
    {
      "item_id": "30b2ede66f:129",
      "text": "在 pixel window（像素窗口）中。",
      "ascii_letters": 11,
      "cjk_chars": 6
    },
    {
      "item_id": "30b2ede66f:132",
      "text": "XPU 现在支持输出 OpenEXR 图像的完整 metadata，包括 data 和 display windows（数据窗口和显示窗口）。RMAN-21507",
      "ascii_letters": 40,
      "cjk_chars": 23
    },
    {
      "item_id": "30b2ede66f:133",
      "text": "XPU 现在支持 cpuTime builtin AOV（内建 AOV）。PRMAN-3023",
      "ascii_letters": 28,
      "cjk_chars": 6
    },
    {
      "item_id": "30b2ede66f:134",
      "text": "XPU 现在支持 PxrSphereCamera。PRMAN-2942",
      "ascii_letters": 23,
      "cjk_chars": 4
    },
    {
      "item_id": "30b2ede66f:135",
      "text": "XPU 现在支持 matte geometry（遮罩几何体）。RMAN-21289",
      "ascii_letters": 20,
      "cjk_chars": 9
    },
    {
      "item_id": "30b2ede66f:136",
      "text": "XPU 现在支持 holdout 工作流（__illumholdout light groups 除外）。RMAN-21290",
      "ascii_letters": 37,
      "cjk_chars": 9
    },
    {
      "item_id": "30b2ede66f:137",
      "text": "XPU 现在支持 shadows 和 invshadows lpe prefix。RMAN-22350",
      "ascii_letters": 33,
      "cjk_chars": 5
    },
    {
      "item_id": "30b2ede66f:138",
      "text": "PxrAovLights 现在在 XPU 中受支持。RMAN-19950",
      "ascii_letters": 19,
      "cjk_chars": 7
    },
    {
      "item_id": "30b2ede66f:139",
      "text": "修复了在没有显式 \"z\" 或 \"Z\" Display 时，XPU 中 DisplayChannel \"id\" \"filter\" \"zmin\" 的功能。",
      "ascii_letters": 38,
      "cjk_chars": 14
    },
    {
      "item_id": "30b2ede66f:140",
      "text": "修复了使用 PxrDisplayFilterCombiner 或 PxrSampleFilterCombiner 时出现的虚假错误。",
      "ascii_letters": 47,
      "cjk_chars": 14
    },
    {
      "item_id": "30b2ede66f:143",
      "text": "XPU 现在支持曲线上的 minwidth。RMAN-21802",
      "ascii_letters": 15,
      "cjk_chars": 8
    },
    {
      "item_id": "30b2ede66f:144",
      "text": "XPU 现在支持 Option 和 Attribute \"dice\" \"offscreenmultiplier\"。此前只支持硬编码值 1。",
      "ascii_letters": 41,
      "cjk_chars": 14
    },
    {
      "item_id": "30b2ede66f:160",
      "text": "在 XPU 中实现了 uniform 和 constant string primvar 支持。PRMAN-3050",
      "ascii_letters": 36,
      "cjk_chars": 8
    },
    {
      "item_id": "30b2ede66f:171",
      "text": "XPU 现在完整支持内部体积聚合（Lama combiner networks（Lama 组合器网络）除外）。RMAN-19743",
      "ascii_letters": 31,
      "cjk_chars": 19
    },
    {
      "item_id": "30b2ede66f:194",
      "text": "修复了缺失的 ModifyLightInstance 功能。RMAN-23897",
      "ascii_letters": 23,
      "cjk_chars": 8
    },
    {
      "item_id": "30b2ede66f:195",
      "text": "Integrators（积分器）",
      "ascii_letters": 11,
      "cjk_chars": 3
    },
    {
      "item_id": "30b2ede66f:196",
      "text": "clampDepth 和 clampLuminance 参数现在已为 PxrPathTracer 实现。LPE 的 noclamp;prefix 现在可以正常工作。RMAN-22803、PRMAN-2939",
      "ascii_letters": 62,
      "cjk_chars": 18
    },
    {
      "item_id": "30b2ede66f:198",
      "text": "所有 XPU 积分器现在都可以输出 geometric AOVs（几何 AOV）。RMAN-20492",
      "ascii_letters": 23,
      "cjk_chars": 14
    },
    {
      "item_id": "30b2ede66f:210",
      "text": "用于查找 user attributes。",
      "ascii_letters": 14,
      "cjk_chars": 4
    },
    {
      "item_id": "30b2ede66f:217",
      "text": "在 XPU 中，PxrSurface \"diffuseTransmissionColor\" 现在会加入 diffuse albedo AOV（漫反照率 AOV），这与 RIS 一样。此前只有 \"diffuseColor\" 会贡献到 diffuse albedo（漫反照率）。PRMAN-2932",
      "ascii_letters": 89,
      "cjk_chars": 27
    },
    {
      "item_id": "30b2ede66f:224",
      "text": "XPU 现在会正确归一化累积多个 lobe normals（lobe 法线）的 user lobes（用户 lobe）。这修正了用于收集降噪法线的标准 LPE 输出。RMAN-20777、PRMAN-2934、PRMAN-3008",
      "ascii_letters": 48,
      "cjk_chars": 34
    },
    {
      "item_id": "30b2ede66f:230",
      "text": "MaterialX Lama",
      "ascii_letters": 13,
      "cjk_chars": 0
    },
    {
      "item_id": "30b2ede66f:232",
      "text": "XPU Features and Limitations（XPU 功能与限制）",
      "ascii_letters": 28,
      "cjk_chars": 5
    },
    {
      "item_id": "30b2ede66f:235",
      "text": "= 1（Chiang），并支持 mode、followTopology 和 sssSubset 参数。",
      "ascii_letters": 33,
      "cjk_chars": 6
    },
    {
      "item_id": "30b2ede66f:236",
      "text": "在 LamaSurface 中新增对 utilityColor、utilityFloat、utilityInt 的支持。RMAN-23212",
      "ascii_letters": 49,
      "cjk_chars": 8
    },
    {
      "item_id": "30b2ede66f:237",
      "text": "LamaDielectric 和 LamaGeneralizedSchlick 现在在计算 thin shadows（薄阴影）时可正确支持 transmissionTint、shadowFresnelFront 和 shadowFresnelBack 参数。RMAN-24088",
      "ascii_letters": 102,
      "cjk_chars": 18
    },
    {
      "item_id": "30b2ede66f:238",
      "text": "为 LamaConductor、LamaDielectric、LamaGeneralizedSchlick、LamaIridescence 新增了各向异性支持。",
      "ascii_letters": 64,
      "cjk_chars": 10
    },
    {
      "item_id": "30b2ede66f:240",
      "text": "修复了 LamaDielectric 和 LamaGeneralizedSchlick 中体积散射各向异性相关的错误。RMAN-24081",
      "ascii_letters": 40,
      "cjk_chars": 18
    },
    {
      "item_id": "30b2ede66f:241",
      "text": "XPU 中的 Lama 节点现在会像 RIS 对应实现一样发出 Tangent user lobes（Tangent 用户 lobe）。RMAN-24118",
      "ascii_letters": 41,
      "cjk_chars": 18
    },
    {
      "item_id": "30b2ede66f:243",
      "text": "PxrSurface",
      "ascii_letters": 10,
      "cjk_chars": 0
    },
    {
      "item_id": "30b2ede66f:244",
      "text": "修复了 PxrSurface 中 back diffuse transmit lobe（背面漫透射 lobe）的 LPE 输出问题。RMAN-22879",
      "ascii_letters": 44,
      "cjk_chars": 14
    },
    {
      "item_id": "30b2ede66f:245",
      "text": "在 XPU PxrSurface 中实现了 \"irradianceTint\" 参数。PRMAN-3088",
      "ascii_letters": 32,
      "cjk_chars": 7
    },
    {
      "item_id": "30b2ede66f:247",
      "text": "PxrSurface 参数 \"iridescenceFlip\" 现在已在 XPU 中实现。",
      "ascii_letters": 28,
      "cjk_chars": 9
    },
    {
      "item_id": "30b2ede66f:248",
      "text": "修复了 XPU PxrSurface 中的一个错误：只有当 \"diffuseDoubleSided\" 为 1 时才会发生漫透射。（与 RIS 相同。）",
      "ascii_letters": 34,
      "cjk_chars": 24
    },
    {
      "item_id": "30b2ede66f:249",
      "text": "修复了 PxrMatteID OSL 节点与 PxrSurface 结合使用时发生的崩溃。RMAN-23760",
      "ascii_letters": 27,
      "cjk_chars": 16
    },
    {
      "item_id": "30b2ede66f:250",
      "text": "Patterns（图案）",
      "ascii_letters": 8,
      "cjk_chars": 2
    },
    {
      "item_id": "30b2ede66f:251",
      "text": "PxrDirt 和 PxrCurvature 这两个 pattern（图案节点）现在已在 XPU 中受支持。RMAN-22327",
      "ascii_letters": 33,
      "cjk_chars": 16
    },
    {
      "item_id": "30b2ede66f:253",
      "text": "次表面散射章节（Subsurface）",
      "ascii_letters": 10,
      "cjk_chars": 7
    },
    {
      "item_id": "30b2ede66f:255",
      "text": "在 XPU PxrSurface 中实现了位于次表面散射（以及 subsurface singlescatter（次表面单次散射））之上的 Clearcoat（清漆层）。（位于其他 lobe 之上的 Clearcoat 此前已经可用。）PRMAN-3080",
      "ascii_letters": 63,
      "cjk_chars": 40
    },
    {
      "item_id": "30b2ede66f:256",
      "text": "XPU 中的次表面散射现在会遵循 \"maxdiffusedepth\" Attribute（属性）。PRMAN-3070",
      "ascii_letters": 32,
      "cjk_chars": 14
    },
    {
      "item_id": "30b2ede66f:257",
      "text": "此前，PxrSurface 会将 subsurface singlescatter（次表面单次散射）归类为 diffuse（漫射）。现在它会被归类为 specular（镜面反射），与 RIS 匹配。PRMAN-2990",
      "ascii_letters": 56,
      "cjk_chars": 31
    },
    {
      "item_id": "30b2ede66f:258",
      "text": "PxrSurface 的 subsurface singlescatter（次表面单次散射）中的多个错误已修复；结果现在与 RIS 匹配。RMAN-22629、PRMAN-3033",
      "ascii_letters": 45,
      "cjk_chars": 24
    },
    {
      "item_id": "30b2ede66f:259",
      "text": "如果 PxrSurface \"",
      "ascii_letters": 10,
      "cjk_chars": 2
    },
    {
      "item_id": "30b2ede66f:264",
      "text": "Glass and glass single scattering（玻璃与玻璃单次散射）",
      "ascii_letters": 29,
      "cjk_chars": 9
    },
    {
      "item_id": "30b2ede66f:265",
      "text": "修复了一个 XPU 问题：在 PxrSurface 上启用 thinGlass 时，IOR 行为过去与 RIS 不匹配。RMAN-22761、PRMAN-2963",
      "ascii_letters": 37,
      "cjk_chars": 20
    },
    {
      "item_id": "30b2ede66f:273",
      "text": "LamaDielectric 和 LamaGeneralizedSchlick XPU shaders（着色器）现在完整支持单次散射（scatterColor 参数），并且所有情况下都会正确应用体积吸收。RMAN-22927",
      "ascii_letters": 62,
      "cjk_chars": 33
    },
    {
      "item_id": "30b2ede66f:274",
      "text": "XPU 现在支持在带有 Attribute \"trace\" \"intersectpriority\" 的 nested dielectrics（嵌套电介质）上正确恢复 \"outside IOR\"（外部 IOR）。这包括正确处理 Attribute \"shade\" \"indexofrefraction\"。请注意，phantom hits（幻影命中）（内部优先级较低的 intersectpriority）尚未实现。RMAN-22775",
      "ascii_letters": 127,
      "cjk_chars": 46
    },
    {
      "item_id": "30b2ede66f:276",
      "text": "XPU 现在支持 PxrPathTracer 的 accumOpacity 功能，用于通过玻璃等折射表面计算部分 alpha。目前只有 PxrSurface 支持此功能。RMAN-20465",
      "ascii_letters": 47,
      "cjk_chars": 31
    },
    {
      "item_id": "30b2ede66f:277",
      "text": "Hair and Fur（毛发与皮毛）",
      "ascii_letters": 10,
      "cjk_chars": 5
    },
    {
      "item_id": "30b2ede66f:278",
      "text": "实现了 XPU PxrChiangHair 的 \"glowColor\" 和 \"glowGain\" 参数。PRMAN-3076",
      "ascii_letters": 38,
      "cjk_chars": 7
    },
    {
      "item_id": "30b2ede66f:279",
      "text": "XPU PxrChiangHair 在 RenderMan 27 中不再遵循 RenderMan 24 向后兼容模式。",
      "ascii_letters": 34,
      "cjk_chars": 12
    },
    {
      "item_id": "30b2ede66f:280",
      "text": "纹理处理章节（Texturing）",
      "ascii_letters": 9,
      "cjk_chars": 6
    },
    {
      "item_id": "30b2ede66f:285",
      "text": "filter type",
      "ascii_letters": 10,
      "cjk_chars": 0
    },
    {
      "item_id": "30b2ede66f:288",
      "text": "XPU 中实现了两种纹理 wrap mode：black、mirror。RMAN-20096",
      "ascii_letters": 26,
      "cjk_chars": 8
    },
    {
      "item_id": "30b2ede66f:289",
      "text": "通过 RIB 中的 Options、DCCs 中可实时编辑的 Options，以及 rendermn.ini，为 XPU 带来了对 ptexturemaxfiles 的支持。同时也支持在 rendermn.ini 中为 ptex 缓存和基于 atlas 的纹理缓存设置纹理缓存大小。RMAN-23542",
      "ascii_letters": 75,
      "cjk_chars": 47
    },
    {
      "item_id": "30b2ede66f:294",
      "text": "统计信息章节（Statistics）",
      "ascii_letters": 10,
      "cjk_chars": 6
    },
    {
      "item_id": "30b2ede66f:300",
      "text": "RenderMan 在 RIS 和 XPU 中，用于 \"variance\" 自适应度量的默认 PixelVariance 已从 0.015 改为 0.05。RMAN-20447",
      "ascii_letters": 40,
      "cjk_chars": 17
    },
    {
      "item_id": "30b2ede66f:302",
      "text": "Image Outputs and Displays（图像输出与显示）",
      "ascii_letters": 23,
      "cjk_chars": 7
    },
    {
      "item_id": "30b2ede66f:303",
      "text": "为 PxrBackgroundSampleFilter 添加了两个新参数：\"aov\" 和 \"aovAlpha\"。与 PxrBackgroundDisplayFilter 中用户可以修改用于读取/写入结果的 AOV 类似，现在对应的 sample filter（采样滤镜）也加入了同样功能。RMAN-22740",
      "ascii_letters": 81,
      "cjk_chars": 46
    },
    {
      "item_id": "30b2ede66f:307",
      "text": "在具有反射/折射的 subsurface scattering（次表面散射）的对象上，RIS27（以及 RIS26）中的 PxrAovLights 给出的结果与 RIS25 不同。现在通过新的 PxrAovLight \"excludeSubsurface\" 参数修复了这一点。将 \"excludeSubsurface\" 参数保持为 1 可匹配 RIS25，设为 0 可匹配 RIS26。",
      "ascii_letters": 92,
      "cjk_chars": 57
    },
    {
      "item_id": "30b2ede66f:308",
      "text": "添加了一个参数，允许在 PxrSphereCamera 和 PxrCylinderCamera 中对 screen window（屏幕窗口）进行归一化。",
      "ascii_letters": 44,
      "cjk_chars": 22
    },
    {
      "item_id": "30b2ede66f:312",
      "text": "PxrPortalLight 现在支持标准 emission focus（发射聚焦）参数。PRMAN-3000",
      "ascii_letters": 32,
      "cjk_chars": 12
    },
    {
      "item_id": "30b2ede66f:314",
      "text": "当颜色为黑色时，PxrMarschnerHair 的默认 albedo（反照率）现在为 1e-5，而不是 0.18。RMAN-22882",
      "ascii_letters": 27,
      "cjk_chars": 19
    },
    {
      "item_id": "30b2ede66f:315",
      "text": "PxrDisneyBsdf 中的 \"subsurface\" 参数已改为 \"subsurfaceMult\"，以避免与对应的 OSL subsurface closure（次表面闭包）关键字冲突。RMAN-20531",
      "ascii_letters": 61,
      "cjk_chars": 24
    },
    {
      "item_id": "30b2ede66f:319",
      "text": "修复了 PxrDispVectorLayer 和 PxrDispScalarLayer 在第 4 层缺少 \"Subtraction\" 运算符的问题。如果你在第 4 层使用除 \"Add\" 或 \"Over\" 以外的任何模式，这可能导致外观差异。RMAN-23474",
      "ascii_letters": 58,
      "cjk_chars": 41
    },
    {
      "item_id": "30b2ede66f:320",
      "text": "现在可以使用 rendermn.ini 通过 \"/prman/osl/\" 前缀设置默认 OSL options（OSL 选项）。例如 \"/prman/osl/clearmemory 1\"。RMAN-22403",
      "ascii_letters": 55,
      "cjk_chars": 18
    },
    {
      "item_id": "30b2ede66f:321",
      "text": "在 PxrRoundCube pattern 中，如果未提供 Nref 但提供了 Pref，现在会自动计算 Nref。RMAN-23583",
      "ascii_letters": 35,
      "cjk_chars": 18
    },
    {
      "item_id": "30b2ede66f:322",
      "text": "PxrBumpMixer 现在具有逐层 \"enable\" toggle（切换）。RMAN-23598",
      "ascii_letters": 28,
      "cjk_chars": 8
    },
    {
      "item_id": "30b2ede66f:324",
      "text": "为 PxrManifold3D 添加了新的 offset、scale 和 rotation 变换参数。RMAN-23582",
      "ascii_letters": 35,
      "cjk_chars": 11
    },
    {
      "item_id": "30b2ede66f:326",
      "text": "OSL 现在允许从 trace-hit geometry（追踪命中几何体）获取 primitive \"u\" 和 \"v\"，方式是通过",
      "ascii_letters": 30,
      "cjk_chars": 20
    },
    {
      "item_id": "30b2ede66f:329",
      "text": "PxrEnvDayLight 和 PxrDomeLight 现在新增参数 \"cameraVisibleAlpha\"，用于在 camera 可见时控制它们的 alpha 贡献。目前该参数仅适用于 PxrPathTracer。此外，无论 PxrPathTracer 中是否开启 accumOpacity，这些灯光的 alpha 贡献行为现在都保持一致。RMAN-21766、RMAN-23761",
      "ascii_letters": 106,
      "cjk_chars": 54
    },
    {
      "item_id": "30b2ede66f:330",
      "text": "PxrNormalMap 的 surface gradient（表面梯度）输出（resultNG）已翻转。此前 PxrNormalMap 中生成的 normals（法线）使用翻转后的 surface gradient 来生成法线输出；如果该 surface gradient 被另一个 pattern（例如 PxrBumpMixer）用于生成 normals（法线），就会产生不匹配。现在通过材质网络得到的结果应更加一致。现有网络如果使用 PxrNormalMap 的 resultNG 输出，并且想保留旧行为，就需要更新：在 PxrNormalMap 上设置 \"invertBump\"、更改 PxrBumpMixer 模式，或用 PxrArithmetic 节点将 resultNG 乘以 -1。RMAN-23878",
      "ascii_letters": 189,
      "cjk_chars": 110
    },
    {
      "item_id": "30b2ede66f:331",
      "text": "PxrMultiTexture 现在在连接非 hex manifold（非六边形流形）时不会应用 \"InvertT\"。这与其他 manifolds 的行为一致。这是一个破坏外观兼容性的变更；RenderMan 27 之前的场景如果包含连接到 PxrMultiTexture 的非 hex manifold（非六边形流形）（例如 PxrRoundCube/PxrTileManifold/(non-hexmode)PxrRandomTextureManifold），且 \"InvertT\" 保持开启，可能需要更新。在 manifold 上切换 \"InvertT\" 会把纹理翻回先前外观。PxrRoundCube 中已添加一个全局 \"InvertT\" 参数，以帮助实现这一点。RMAN-23877",
      "ascii_letters": 183,
      "cjk_chars": 105
    },
    {
      "item_id": "30b2ede66f:332",
      "text": "LamaGeneralizedSchlick 的 \"energyCompensation\" 参数默认值已从 0.0 改为 1.0，以匹配其他 Lama 材质中的默认值。",
      "ascii_letters": 44,
      "cjk_chars": 22
    },
    {
      "item_id": "30b2ede66f:335",
      "text": "Texture Manager 的默认格式已更新为更现代、ACES-compliant（符合 ACES）的标准。",
      "ascii_letters": 31,
      "cjk_chars": 17
    },
    {
      "item_id": "30b2ede66f:337",
      "text": "Texture Manager UI 现在支持 HiDPI 屏幕。",
      "ascii_letters": 21,
      "cjk_chars": 6
    },
    {
      "item_id": "30b2ede66f:338",
      "text": "Current Limitations（当前限制）：OpenImageIO backend（后端）：",
      "ascii_letters": 36,
      "cjk_chars": 6
    },
    {
      "item_id": "30b2ede66f:339",
      "text": "Bump Roughness map 转换没有 gaussian refit 选项",
      "ascii_letters": 29,
      "cjk_chars": 6
    },
    {
      "item_id": "30b2ede66f:343",
      "text": "以下 user attributes（用户属性）：",
      "ascii_letters": 14,
      "cjk_chars": 6
    },
    {
      "item_id": "30b2ede66f:344",
      "text": "如果存在，可以覆盖 PxrTexture() OSL shader 参数 \"mipBias\" 和 \"maxResolution\"。CUSP-8416",
      "ascii_letters": 43,
      "cjk_chars": 11
    },
    {
      "item_id": "30b2ede66f:345",
      "text": "PxrBumpRoughness 可以读取由 OpenImageIO/maketx 生成的 6-channel bump roughness maps（6 通道 bump roughness 贴图）。RMAN-9917",
      "ascii_letters": 74,
      "cjk_chars": 12
    },
    {
      "item_id": "30b2ede66f:346",
      "text": "小写 <udim> 已弃用，改用 USD-compliant（符合 USD）的大写标准 <UDIM>。RMAN-22929",
      "ascii_letters": 27,
      "cjk_chars": 14
    },
    {
      "item_id": "30b2ede66f:347",
      "text": "将 texture manager 使用的默认 compression（压缩）改为 zip。RMAN-23752",
      "ascii_letters": 32,
      "cjk_chars": 10
    },
    {
      "item_id": "30b2ede66f:348",
      "text": "当尝试把 non-tiled OpenEXR 图像用作纹理时，RenderMan 不再 dump core（转储核心）。",
      "ascii_letters": 32,
      "cjk_chars": 17
    },
    {
      "item_id": "30b2ede66f:352",
      "text": "这个 maketx 选项）发出警告。RMAN-23801、RMAN-23787、RMAN-23785",
      "ascii_letters": 18,
      "cjk_chars": 8
    },
    {
      "item_id": "30b2ede66f:354",
      "text": "已从 PxrTexture、PxrLayeredTexture、PxrNormalMap、PxrBump pattern nodes（图案节点）中移除已弃用参数 atlasStyle",
      "ascii_letters": 68,
      "cjk_chars": 14
    },
    {
      "item_id": "30b2ede66f:355",
      "text": "统计信息章节（Statistics）",
      "ascii_letters": 10,
      "cjk_chars": 6
    },
    {
      "item_id": "30b2ede66f:358",
      "text": "修复了在加载 heavy scene（重场景）并启用许多 stats metrics（统计指标）时，stats system（统计系统）内部出现的 deadlocks（死锁）。PRMAN-3403",
      "ascii_letters": 47,
      "cjk_chars": 30
    },
    {
      "item_id": "30b2ede66f:359",
      "text": "修复了 stats configuration（统计配置）中带有环境变量时 Windows \"rewrite\" 错误。RMAN-23323",
      "ascii_letters": 36,
      "cjk_chars": 17
    },
    {
      "item_id": "30b2ede66f:360",
      "text": "JSON stats report（JSON 统计报告）现在会在 live rendering（实时渲染）中禁用，与 legacy XML stats report（旧版 XML 统计报告）的行为一致。RMAN-23633",
      "ascii_letters": 59,
      "cjk_chars": 27
    },
    {
      "item_id": "30b2ede66f:361",
      "text": "现在可以使用新的显式 Listener flag（Listener 标志）\"enabled\"，启用或禁用在 stats.ini 文件中配置的 Listener。RMAN-23560",
      "ascii_letters": 47,
      "cjk_chars": 24
    },
    {
      "item_id": "30b2ede66f:362",
      "text": "JSON Report（JSON 报告）变更",
      "ascii_letters": 14,
      "cjk_chars": 4
    },
    {
      "item_id": "30b2ede66f:364",
      "text": "\"jsonEnabled\" 选项会与现有 \"jsonFilename\" 选项配合使用，用于生成 JSON stats report（JSON 统计报告）。\"statistics:jsonMetrics\" 选项可用于控制最终 JSON report 的内容。它的值可以设为两个值之一：'standard' 或 'detailed'。RMAN-23633",
      "ascii_letters": 93,
      "cjk_chars": 45
    },
    {
      "item_id": "30b2ede66f:366",
      "text": "改进了 stportal 在呈现 JSON Report 时对 process memory statistics（进程内存统计）的命名。\"current\" 已重命名为 \"heap\"；\"maximum\" 已重命名为 \"peak\"。",
      "ascii_letters": 63,
      "cjk_chars": 27
    },
    {
      "item_id": "30b2ede66f:367",
      "text": "Live Stats（实时统计）变更",
      "ascii_letters": 9,
      "cjk_chars": 6
    },
    {
      "item_id": "30b2ede66f:368",
      "text": "已将所有 DCCs 的 Live Stats 面板升级为使用 stportal UI modules（UI 模块）。RMAN-22746",
      "ascii_letters": 36,
      "cjk_chars": 14
    },
    {
      "item_id": "30b2ede66f:370",
      "text": "Live Stats pie charts（饼图）现在支持 XPU timers 和 counters（XPU 计时器与计数器）。RMAN-20391",
      "ascii_letters": 42,
      "cjk_chars": 14
    },
    {
      "item_id": "30b2ede66f:371",
      "text": "Live Stats 窗口中的 \"Connection\" section（\"Connection\" 区域）已被一个小型 status",
      "ascii_letters": 42,
      "cjk_chars": 12
    },
    {
      "item_id": "30b2ede66f:374",
      "text": "stportal 更新",
      "ascii_letters": 8,
      "cjk_chars": 2
    },
    {
      "item_id": "30b2ede66f:375",
      "text": "stportal 中的 live stream（实时流）\"Raw Data\" dock window（停靠窗口）已拆分为可排序的 Timer、Memory 和 Counter dock windows（停靠窗口）。RMAN-23516",
      "ascii_letters": 68,
      "cjk_chars": 22
    },
    {
      "item_id": "30b2ede66f:376",
      "text": "Memory tracking（内存跟踪）变更",
      "ascii_letters": 14,
      "cjk_chars": 6
    },
    {
      "item_id": "30b2ede66f:378",
      "text": "Tracked memory entries（受跟踪的内存条目）（位于",
      "ascii_letters": 20,
      "cjk_chars": 10
    },
    {
      "item_id": "30b2ede66f:380",
      "text": "Peak memory（峰值内存）现在必须由 Listener plugins（Listener 插件）汇总。JSON Report plugin（JSON Report 插件）已更新，可汇总并报告峰值。",
      "ascii_letters": 59,
      "cjk_chars": 26
    },
    {
      "item_id": "30b2ede66f:384",
      "text": "\"variance-v22\" 自适应度量在 RIS 中现在称为 \"relativevariance\"。RMAN-22556",
      "ascii_letters": 32,
      "cjk_chars": 11
    },
    {
      "item_id": "30b2ede66f:385",
      "text": "Image Outputs and Displays（图像输出与显示）",
      "ascii_letters": 23,
      "cjk_chars": 7
    },
    {
      "item_id": "30b2ede66f:386",
      "text": "DDC files（DDC 文件）（checkpointing deep renders（检查点深度渲染）时产生的中间文件）现在可以用 sho 和 dsview 查看。",
      "ascii_letters": 44,
      "cjk_chars": 25
    },
    {
      "item_id": "30b2ede66f:388",
      "text": "修复了 PxrShadowDisplay filter 和 lpe \"shadow\" flag（标志）在 interactive setting（交互式设置）中可能失效的问题。RMAN-23515",
      "ascii_letters": 57,
      "cjk_chars": 20
    },
    {
      "item_id": "30b2ede66f:393",
      "text": "Dicing（切分）现在在判断 object（对象）是否 offscreen（屏幕外）时，会考虑 image overscan（图像 overscan）。RMAN-23417",
      "ascii_letters": 46,
      "cjk_chars": 20
    },
    {
      "item_id": "30b2ede66f:397",
      "text": "改进了对 deformation motion blurred general polygon meshes（带变形运动模糊的一般多边形网格）的处理，尤其是在 degenerate faces（退化面）通过运动模糊变成 non-degenerate faces（非退化面）的情况下。PRMAN-3375",
      "ascii_letters": 82,
      "cjk_chars": 45
    },
    {
      "item_id": "30b2ede66f:400",
      "text": "PxrUnified 现在支持 aggregate volumes（聚合体积）。请注意，与 PxrPathTracer 不同，PxrUnified 默认不会渲染 aggregate volumes（聚合体积）；用户必须将 volumeAggregate 参数设为 'on' 来显式启用。默认情况下，PxrUnified 也会渲染属于名为 \"globalVolumeAggregate\" 的 aggregate（聚合体），但可以使用 volumeAggregateNameCamera、volumeAggregateNameTransmission、",
      "ascii_letters": 178,
      "cjk_chars": 60
    },
    {
      "item_id": "30b2ede66f:401",
      "text": "和 volumeAggregateNameIndirect 参数覆盖这一行为。RMAN-21848",
      "ascii_letters": 31,
      "cjk_chars": 9
    },
    {
      "item_id": "30b2ede66f:402",
      "text": "修复了 deformation motion blurred aggregate volumes（带变形运动模糊的聚合体积）导致性能远低于预期的问题。RMAN-23036",
      "ascii_letters": 44,
      "cjk_chars": 27
    },
    {
      "item_id": "30b2ede66f:403",
      "text": "修复了 volumetric light sources（体积光源）无法与 bxdf sampling rays（bxdf 采样光线）相交的问题。RMAN-23061",
      "ascii_letters": 46,
      "cjk_chars": 19
    },
    {
      "item_id": "30b2ede66f:406",
      "text": "修复了使用 interior volume aggregates（内部体积聚合）和 Lama shaders（Lama 着色器）时的内存泄漏。RMAN-23430",
      "ascii_letters": 43,
      "cjk_chars": 21
    },
    {
      "item_id": "30b2ede66f:407",
      "text": "修复了在 PxrPathTracer 中设置 numIndirectSamples > 1 时 aggregate volumes（聚合体积）出现的伪影。RMAN-23501",
      "ascii_letters": 51,
      "cjk_chars": 17
    },
    {
      "item_id": "30b2ede66f:410",
      "text": "修复了 4-channel light textures（4 通道灯光纹理）渲染不正确的错误。RMAN-23570",
      "ascii_letters": 24,
      "cjk_chars": 17
    },
    {
      "item_id": "30b2ede66f:411",
      "text": "改进了 high face count（高面数）polymeshes（多边形网格）上 mesh light（网格灯）的初始化时间。RMAN-23602",
      "ascii_letters": 36,
      "cjk_chars": 21
    },
    {
      "item_id": "30b2ede66f:412",
      "text": "修复了 high face count（高面数）的 mesh light polygon meshes（网格灯多边形网格）无法正确采样的问题。RMAN-23602",
      "ascii_letters": 39,
      "cjk_chars": 24
    },
    {
      "item_id": "30b2ede66f:413",
      "text": "修复了 light selection（灯光选择）中的一个错误，该错误会阻止 Option \"lighting\" \"float minimumestimate\" 的较低值生效。PRMAN-3369",
      "ascii_letters": 53,
      "cjk_chars": 25
    },
    {
      "item_id": "30b2ede66f:414",
      "text": "Integrators（积分器）",
      "ascii_letters": 11,
      "cjk_chars": 3
    },
    {
      "item_id": "30b2ede66f:415",
      "text": "修复了 PxrUnified 中的一个错误：sss 会被重复写入 diffuse LPE（漫反射 LPE）两次。CUSP-8429",
      "ascii_letters": 30,
      "cjk_chars": 20
    },
    {
      "item_id": "30b2ede66f:417",
      "text": "PxrPathTracer 的 \"rouletteDepth\" 默认值已从 4 改为 1。\"rouletteDepth\" 0 会被钳制为 1（而不是完全关闭 Russian roulette（俄罗斯轮盘））。",
      "ascii_letters": 54,
      "cjk_chars": 25
    },
    {
      "item_id": "30b2ede66f:418",
      "text": "在 RIS 和 XPU 中，PxrPathTracer 和 PxrUnified 的 numLightSamples 默认值都已从 1 改为 2。",
      "ascii_letters": 44,
      "cjk_chars": 13
    },
    {
      "item_id": "30b2ede66f:420",
      "text": "修复了一个错误：该错误可能导致 texture() 和 texture3d() 返回的 alpha values（alpha 值）derivatives（导数）异常，并可能错误缩放 texture3d() 返回的 derivatives（导数）。RMAN-22281",
      "ascii_letters": 65,
      "cjk_chars": 35
    },
    {
      "item_id": "30b2ede66f:421",
      "text": "RIS 中 PxrSurface 的 subsurface singlescatter LPE（次表面单次散射 LPE）已从 CSDL 改为单次 specular bounce（镜面反弹）CSL。这使 RIS 中的 singlescatter LPE 与 XPU 匹配。它也更接近常规 subsurface scattering（次表面散射），后者是单次 diffuse bounce（漫反射反弹）（CDL），但在 R25 及更早版本中曾是两次反弹（CDDL）。常用的 singlescatter LPE \"CS7[DS]*L\" 仍然有效。RMAN-22629",
      "ascii_letters": 151,
      "cjk_chars": 69
    },
    {
      "item_id": "30b2ede66f:422",
      "text": "OSL support（OSL 支持）现在会在使用 getmessage() 从 trace() 调用获取值时，将 RenderMan 名称 \"Ngn\" 别名到 OSL 等价名称 \"Ng\"。RMAN-22770",
      "ascii_letters": 49,
      "cjk_chars": 25
    },
    {
      "item_id": "30b2ede66f:424",
      "text": "修复了一个错误：当 primstr substitution（primstr 替换）失败时，可能出现关于缺失 \"\" textures（纹理）的错误。PRMAN-3297",
      "ascii_letters": 39,
      "cjk_chars": 26
    },
    {
      "item_id": "30b2ede66f:427",
      "text": "修复了 PxrSurface 中的一个问题：带 presence 的对象在被 matted（遮罩为 matte）时，仍会向 camera（摄影机）渲染 utility pattern（实用图案）。RMAN-23585",
      "ascii_letters": 53,
      "cjk_chars": 31
    },
    {
      "item_id": "30b2ede66f:428",
      "text": "由 LamaDiffuse、LamaTranslucent 和 LamaSheen 写入的 UserTangent lobe（UserTangent 波瓣）现在与所有其他 Lama base nodes（Lama 基础节点）使用的计算保持一致。RMAN-24157",
      "ascii_letters": 82,
      "cjk_chars": 27
    },
    {
      "item_id": "30b2ede66f:429",
      "text": "RIS LamaSSS 在带有 bump-mapped（凹凸贴图）\"sssNormal\" 的情况下执行 subsurface scattering（次表面散射）时，渲染结果比相同 albedo（反照率）的 RIS LamaDiffuse 更暗，也比 \"sssRadius\" 为 [0,0,0]（会将 sss 切换为 diffuse（漫反射））的 RIS LamaSSS 更暗。此问题已修复，因此在 bump-mapped surface（凹凸贴图表面）上，LamaSSS subsurface scattering 与另外两种情况保持一致。RMAN-24115",
      "ascii_letters": 146,
      "cjk_chars": 73
    },
    {
      "item_id": "30b2ede66f:431",
      "text": "向 rendermn.ini 文件添加了 \"prman/missingfilewarning\" 选项；如果 files（文件）（textures 等）在磁盘上找不到，则显示 warning（警告）。RMAN-23515",
      "ascii_letters": 58,
      "cjk_chars": 25
    },
    {
      "item_id": "30b2ede66f:432",
      "text": "降噪器章节（Denoiser）",
      "ascii_letters": 8,
      "cjk_chars": 5
    },
    {
      "item_id": "30b2ede66f:435",
      "text": "为 denoiser config（降噪器配置）添加了 maxTileSize 选项。如果 tile resolution（瓦片分辨率）（X 或 Y 维度）高于 maxTileSize，则改用 maxTileSize。RMAN-23024",
      "ascii_letters": 67,
      "cjk_chars": 26
    },
    {
      "item_id": "30b2ede66f:440",
      "text": "Stylized Looks（风格化外观）",
      "ascii_letters": 13,
      "cjk_chars": 5
    },
    {
      "item_id": "30b2ede66f:441",
      "text": "PxrStylizedControl：",
      "ascii_letters": 18,
      "cjk_chars": 0
    },
    {
      "item_id": "30b2ede66f:442",
      "text": "新的 in-shader（着色器内）Line Detect 模式：Curvature Thin Line 和 Sobel Map",
      "ascii_letters": 43,
      "cjk_chars": 9
    },
    {
      "item_id": "30b2ede66f:443",
      "text": "支持用于 artistic Hatching（艺术化排线）和 Toon shadows（卡通阴影）的 trace sets",
      "ascii_letters": 36,
      "cjk_chars": 15
    },
    {
      "item_id": "30b2ede66f:444",
      "text": "用于 Toon 和 Hatching breakup（变化破碎）的 Normal Map 输入",
      "ascii_letters": 28,
      "cjk_chars": 10
    },
    {
      "item_id": "30b2ede66f:446",
      "text": "P projections 的 Size Space scale（Size Space 缩放）",
      "ascii_letters": 35,
      "cjk_chars": 3
    },
    {
      "item_id": "30b2ede66f:447",
      "text": "新增 Primary Hit only 开关，用于在 data passes（数据通道）上抑制 bounce（反弹）",
      "ascii_letters": 30,
      "cjk_chars": 16
    },
    {
      "item_id": "30b2ede66f:448",
      "text": "Output Line / Hatching / Toon 到 downstream PxrMix 和 BxDF",
      "ascii_letters": 42,
      "cjk_chars": 2
    },
    {
      "item_id": "30b2ede66f:449",
      "text": "Custom Output 任意 AOV",
      "ascii_letters": 15,
      "cjk_chars": 2
    },
    {
      "item_id": "30b2ede66f:450",
      "text": "与 physically-based rendering（基于物理的渲染）集成",
      "ascii_letters": 24,
      "cjk_chars": 10
    },
    {
      "item_id": "30b2ede66f:451",
      "text": "支持 interactive and offline Denoiser（交互式和离线 Denoiser）",
      "ascii_letters": 37,
      "cjk_chars": 8
    },
    {
      "item_id": "30b2ede66f:452",
      "text": "PxrStylizedPainterlyBrushControl：",
      "ascii_letters": 32,
      "cjk_chars": 0
    },
    {
      "item_id": "30b2ede66f:453",
      "text": "新的 in-shader（着色器内）Painterly Brush",
      "ascii_letters": 22,
      "cjk_chars": 6
    },
    {
      "item_id": "30b2ede66f:454",
      "text": "On-geo（几何体上）UV / Triplanar / Screen projections（投影）",
      "ascii_letters": 33,
      "cjk_chars": 6
    },
    {
      "item_id": "30b2ede66f:455",
      "text": "从 sample texture（样本纹理）procedurally（程序化地）生成 painterly brushes（绘画笔刷）",
      "ascii_letters": 41,
      "cjk_chars": 15
    },
    {
      "item_id": "30b2ede66f:456",
      "text": "将 Diffuse color 的 Color output（颜色输出）传入 downstream BxDF",
      "ascii_letters": 37,
      "cjk_chars": 8
    },
    {
      "item_id": "30b2ede66f:457",
      "text": "将 painterly normals（绘画风格法线）的 Normal output（法线输出）传入 downstream BxDF",
      "ascii_letters": 42,
      "cjk_chars": 14
    },
    {
      "item_id": "30b2ede66f:458",
      "text": "将用于 vector displacement（矢量位移）的 Normal output（法线输出）传入 downstream PxrDisplace",
      "ascii_letters": 51,
      "cjk_chars": 14
    },
    {
      "item_id": "30b2ede66f:459",
      "text": "与 physically-based rendering（基于物理的渲染）集成",
      "ascii_letters": 24,
      "cjk_chars": 10
    },
    {
      "item_id": "30b2ede66f:460",
      "text": "支持 interactive and offline Denoiser（交互式和离线 Denoiser）",
      "ascii_letters": 37,
      "cjk_chars": 8
    },
    {
      "item_id": "30b2ede66f:461",
      "text": "PxrStylizedPainterlyBrushXPU：",
      "ascii_letters": 28,
      "cjk_chars": 0
    },
    {
      "item_id": "30b2ede66f:462",
      "text": "新的 Painterly Brush XPU Display Filter（显示滤镜）",
      "ascii_letters": 30,
      "cjk_chars": 6
    },
    {
      "item_id": "30b2ede66f:463",
      "text": "带可变 opacity（不透明度）和 brush width（笔刷宽度）的 procedural layers（程序化图层）",
      "ascii_letters": 33,
      "cjk_chars": 18
    },
    {
      "item_id": "30b2ede66f:464",
      "text": "Off-geo（几何体外）painterly brush strokes（绘画笔触）",
      "ascii_letters": 27,
      "cjk_chars": 8
    },
    {
      "item_id": "30b2ede66f:466",
      "text": "Rotation modes（旋转模式）：Random / Degrees / Shading Tangent / Normals，并带 random jitter（随机抖动）",
      "ascii_letters": 59,
      "cjk_chars": 10
    },
    {
      "item_id": "30b2ede66f:467",
      "text": "用于 denoised signals（已降噪信号）的 Custom Tex variation（自定义 Tex 变化）",
      "ascii_letters": 36,
      "cjk_chars": 13
    },
    {
      "item_id": "30b2ede66f:468",
      "text": "基于 camera depth（相机深度）、lighting（照明）、whiteshader 的 Variation（变化）",
      "ascii_letters": 39,
      "cjk_chars": 11
    },
    {
      "item_id": "30b2ede66f:469",
      "text": "Custom Output 任意 AOV",
      "ascii_letters": 15,
      "cjk_chars": 2
    },
    {
      "item_id": "30b2ede66f:470",
      "text": "PxrStylizedCanvasXPU：",
      "ascii_letters": 20,
      "cjk_chars": 0
    },
    {
      "item_id": "30b2ede66f:471",
      "text": "新的 XPU Display Filter（显示滤镜）",
      "ascii_letters": 16,
      "cjk_chars": 6
    },
    {
      "item_id": "30b2ede66f:472",
      "text": "Layer 任意 FG layer（前景层）到 BG layer（背景层），并使用 custom masks（自定义遮罩）",
      "ascii_letters": 30,
      "cjk_chars": 17
    },
    {
      "item_id": "30b2ede66f:473",
      "text": "Layer compositing modes（图层合成模式）：以下保留可选枚举值 Over|Multiply|Screen|Plus|Difference|Divide|Exclusion|Darken|Lighten|Overlay|Soft Light|Hard Light|Color Dodge|Color Burn|Linear Dodge|Linear Burn|Vivid Light|Pin Light|Enhanced Difference",
      "ascii_letters": 182,
      "cjk_chars": 15
    },
    {
      "item_id": "30b2ede66f:474",
      "text": "Custom Output 任意 AOV",
      "ascii_letters": 15,
      "cjk_chars": 2
    },
    {
      "item_id": "30b2ede66f:475",
      "text": "PxrStylizedLinesXPU：",
      "ascii_letters": 19,
      "cjk_chars": 0
    },
    {
      "item_id": "30b2ede66f:476",
      "text": "新的 XPU Display Filter（显示滤镜）",
      "ascii_letters": 16,
      "cjk_chars": 6
    },
    {
      "item_id": "30b2ede66f:477",
      "text": "带 preview modes（预览模式）的 procedural in-filter distortion（滤镜内程序化扭曲）",
      "ascii_letters": 40,
      "cjk_chars": 14
    },
    {
      "item_id": "30b2ede66f:478",
      "text": "In-filter 的 96-preset line breakup textures（滤镜内 96 个预设线条破碎纹理）",
      "ascii_letters": 33,
      "cjk_chars": 13
    },
    {
      "item_id": "30b2ede66f:480",
      "text": "2 种 Line Generation Modes（线条生成模式）：in-filter Variance Line detect（滤镜内方差线条检测），以及来自 PxrStylizedControl 的 upstream in-shader sample-level edge detect（上游着色器内样本级边缘检测）（Curvature Thin Line 和 Sobel Map）",
      "ascii_letters": 125,
      "cjk_chars": 35
    },
    {
      "item_id": "30b2ede66f:481",
      "text": "Custom Output 任意 AOV",
      "ascii_letters": 15,
      "cjk_chars": 2
    },
    {
      "item_id": "30b2ede66f:482",
      "text": "PxrStylizedToonXPU：",
      "ascii_letters": 18,
      "cjk_chars": 0
    },
    {
      "item_id": "30b2ede66f:483",
      "text": "新的 Toon XPU Display Filter（显示滤镜）",
      "ascii_letters": 20,
      "cjk_chars": 6
    },
    {
      "item_id": "30b2ede66f:484",
      "text": "从 PxrStylizedControl 读取 Artistic Toon",
      "ascii_letters": 30,
      "cjk_chars": 3
    },
    {
      "item_id": "30b2ede66f:485",
      "text": "来自 shadow LPE's 的可选 shadow treatment（阴影处理）",
      "ascii_letters": 25,
      "cjk_chars": 9
    },
    {
      "item_id": "30b2ede66f:486",
      "text": "Custom Output 任意 AOV",
      "ascii_letters": 15,
      "cjk_chars": 2
    },
    {
      "item_id": "30b2ede66f:487",
      "text": "PxrStylizedHatchingSampleXPU：",
      "ascii_letters": 28,
      "cjk_chars": 0
    },
    {
      "item_id": "30b2ede66f:488",
      "text": "新的 XPU Hatching Sample Filter（排线样本滤镜）",
      "ascii_letters": 23,
      "cjk_chars": 8
    },
    {
      "item_id": "30b2ede66f:489",
      "text": "Projections（投影）：Screen Space、Triplanar",
      "ascii_letters": 31,
      "cjk_chars": 2
    },
    {
      "item_id": "30b2ede66f:490",
      "text": "Triplanar projections（Triplanar 投影）从 sample-level PxrStylizedControl 读取，以获得更高质量的 filtering（过滤）",
      "ascii_letters": 67,
      "cjk_chars": 15
    },
    {
      "item_id": "30b2ede66f:491",
      "text": "单独 custom textures 与 4-pack custom textures（单独和四联包自定义纹理）",
      "ascii_letters": 32,
      "cjk_chars": 14
    },
    {
      "item_id": "30b2ede66f:492",
      "text": "Custom Output 任意 AOV",
      "ascii_letters": 15,
      "cjk_chars": 2
    },
    {
      "item_id": "30b2ede66f:493",
      "text": "RenderMan for Blender",
      "ascii_letters": 19,
      "cjk_chars": 0
    },
    {
      "item_id": "30b2ede66f:494",
      "text": "随着 RenderMan 中包含 PySide6，Preset Browser（预设浏览器）和 Texture Manager（纹理管理器）的 Qt 版本现在再次可在 Blender 4.x 中使用。RMAN-22808",
      "ascii_letters": 56,
      "cjk_chars": 28
    },
    {
      "item_id": "30b2ede66f:497",
      "text": "已处理一个错误：rigid bodies（刚体）和 dynamic paint（动态绘制）等 dynamics（动力学）在 batch renders（批量渲染）中无法正确渲染。RMAN-22863",
      "ascii_letters": 47,
      "cjk_chars": 30
    },
    {
      "item_id": "30b2ede66f:501",
      "text": "camera roundness 和 density 的最小值都被错误设置为 0.0，而不是 -1.0",
      "ascii_letters": 22,
      "cjk_chars": 15
    },
    {
      "item_id": "30b2ede66f:503",
      "text": "添加了新的 checkbox（复选框），可为 particle emitters（粒子发射器）和 hair particles（毛发粒子）禁用基于 velocity（速度）的 motion blur（运动模糊）",
      "ascii_letters": 55,
      "cjk_chars": 31
    },
    {
      "item_id": "30b2ede66f:504",
      "text": "invert light linking preference（反转灯光链接偏好设置）现在是 scene option（场景选项）。",
      "ascii_letters": 39,
      "cjk_chars": 17
    },
    {
      "item_id": "30b2ede66f:505",
      "text": "package scene operator（打包场景操作符）现在有一个选项，可将场景中所有 texture parameters（纹理参数）切换为全部使用 .tex files（.tex 文件）。",
      "ascii_letters": 48,
      "cjk_chars": 34
    },
    {
      "item_id": "30b2ede66f:506",
      "text": "修复了导致使用 join geometry node（连接几何节点）的 geometry node instances（几何节点实例）无法正常工作的错误。RMAN-23469",
      "ascii_letters": 41,
      "cjk_chars": 29
    },
    {
      "item_id": "30b2ede66f:509",
      "text": "添加了对 Blender 原生 light linking（灯光链接）工作流的支持。请注意，默认情况下此功能关闭，但可以在 scene properties（场景属性）的 Light Linking section（Light Linking 区域）下启用。RMAN-23590",
      "ascii_letters": 69,
      "cjk_chars": 43
    },
    {
      "item_id": "30b2ede66f:510",
      "text": "stylized looks editor（风格化外观编辑器）现在也可以在 scene properties tab（场景属性标签页）的 RenderMan Stylized Looks panel（面板）下找到。RMAN-23591",
      "ascii_letters": 68,
      "cjk_chars": 27
    },
    {
      "item_id": "30b2ede66f:511",
      "text": "interactive denoiser（交互式降噪器）的默认 minimum samples（最小采样数）设置已增至 4。RMAN-22451",
      "ascii_letters": 37,
      "cjk_chars": 19
    },
    {
      "item_id": "30b2ede66f:512",
      "text": "为 particle systems（粒子系统）添加了新的 scale velocity blur 设置。",
      "ascii_letters": 32,
      "cjk_chars": 12
    },
    {
      "item_id": "30b2ede66f:518",
      "text": "token 时，可以使用 Python 的 math 和 random 模块中的函数。例如，",
      "ascii_letters": 21,
      "cjk_chars": 15
    },
    {
      "item_id": "30b2ede66f:522",
      "text": "对于 pointcloud objects（点云对象），如果存在名为 \"velocity\" 的 attribute（属性），我们会使用它来进行 deformation blur（变形模糊）。",
      "ascii_letters": 49,
      "cjk_chars": 28
    },
    {
      "item_id": "30b2ede66f:523",
      "text": "现在可以在 RfB 仍在转换场景时取消 viewport render（视口渲染）或 regular render（常规渲染）。对于 viewport renders，可以点击 progress bar window（进度条窗口）上的 Cancel 按钮来取消渲染。RMAN-24174",
      "ascii_letters": 72,
      "cjk_chars": 43
    },
    {
      "item_id": "30b2ede66f:524",
      "text": "RenderMan for Maya",
      "ascii_letters": 16,
      "cjk_chars": 0
    },
    {
      "item_id": "30b2ede66f:526",
      "text": "找到 hdPrman，则 Maya 2025 可能崩溃。RMAN-22490",
      "ascii_letters": 15,
      "cjk_chars": 7
    },
    {
      "item_id": "30b2ede66f:528",
      "text": "Texture Manager（纹理管理器）不再转换已经是 texture files（纹理文件）但文件名不以 .tex 结尾的 image files（图像文件）。RMAN-23339",
      "ascii_letters": 43,
      "cjk_chars": 29
    },
    {
      "item_id": "30b2ede66f:529",
      "text": "Texture Manager UI 已针对 HiDPI displays（HiDPI 显示器）修复。RMAN-20960",
      "ascii_letters": 38,
      "cjk_chars": 8
    },
    {
      "item_id": "30b2ede66f:530",
      "text": "为 Texture Manager 的 \"Pick...\" buttons（按钮）和 settings UI（设置 UI）添加了 multiselect（多选）功能。添加了 \"Re-convert Updated\" 按钮，用于检查磁盘上的纹理是否已更改。",
      "ascii_letters": 64,
      "cjk_chars": 34
    },
    {
      "item_id": "30b2ede66f:532",
      "text": "修复了以 separate AOV（单独 AOV）输出的 holdouts（遮挡保留对象）没有被 denoised（降噪）的错误。RMAN-22794",
      "ascii_letters": 34,
      "cjk_chars": 23
    },
    {
      "item_id": "30b2ede66f:533",
      "text": "Gobo 和 Blocker Light filters（灯光滤镜）现已弃用。请改用 Cookie 和 Rod filters。",
      "ascii_letters": 39,
      "cjk_chars": 13
    },
    {
      "item_id": "30b2ede66f:534",
      "text": "RenderMan for Katana",
      "ascii_letters": 18,
      "cjk_chars": 0
    },
    {
      "item_id": "30b2ede66f:535",
      "text": "RfK 现在接受 sample filters（采样过滤器）和 display filters（显示过滤器）的 osl 版本。它们会优先于同名的任何 c++ 版本。任何 osl sample filters 和 display filters 都需要在顶层 metadata（元数据）中包含 string rfk_classification = \"samplefilter\" 或 string rfk_classification = \"displayfilter\"，以便 RfK 正确处理。RMAN-21117",
      "ascii_letters": 150,
      "cjk_chars": 53
    },
    {
      "item_id": "30b2ede66f:536",
      "text": "现在支持用于 XPU 的 interactive denoiser（交互式降噪器）。",
      "ascii_letters": 22,
      "cjk_chars": 13
    },
    {
      "item_id": "30b2ede66f:537",
      "text": "interactive denoiser（交互式降噪器）现在可以与 \"it\" image tool（图像工具）配合使用。RMAN-21674",
      "ascii_letters": 34,
      "cjk_chars": 19
    },
    {
      "item_id": "30b2ede66f:539",
      "text": "RfK 现在支持通过逗号分隔的索引字符串选择 multiple gpus（多个 GPU），例如：0,1,2。prmanGlobalStatements.gpuSelection setting（设置）现在是 StringAttribute，而不是单个 IntAttribute。RMAN-22344",
      "ascii_letters": 89,
      "cjk_chars": 32
    },
    {
      "item_id": "30b2ede66f:540",
      "text": "现在，XPU Preview renders（XPU 预览渲染）的 frame number（帧号）会显示在 Catalog（目录）中。",
      "ascii_letters": 38,
      "cjk_chars": 16
    },
    {
      "item_id": "30b2ede66f:542",
      "text": "PxrDisney 和 PxrDisneyBsdf 的 subsurface 参数已重命名为 subsurfaceMult。可使用 shelf script（工具架脚本）来升级 PrmanShadingNodes 中包含这些参数的场景。通过 UsdIn 传入的 Materials（材质）会自动更新。RMAN-23320",
      "ascii_letters": 92,
      "cjk_chars": 42
    },
    {
      "item_id": "30b2ede66f:543",
      "text": "Gobo 和 Blocker Light filters（灯光滤镜）现已弃用。请改用 Cookie 和 Rod filters。",
      "ascii_letters": 39,
      "cjk_chars": 13
    },
    {
      "item_id": "30b2ede66f:544",
      "text": "RenderMan for Houdini",
      "ascii_letters": 19,
      "cjk_chars": 0
    },
    {
      "item_id": "30b2ede66f:545",
      "text": "已隐藏 \"RenderMan Standard Render Vars\" LOP；该 LOP 现已弃用，改为使用新的 \"RenderMan Render Vars\" LOP。RMAN-23115",
      "ascii_letters": 59,
      "cjk_chars": 14
    },
    {
      "item_id": "30b2ede66f:546",
      "text": "已更新 PxrLayeredBlend 和 PxrLayer，使 backgroundRGB/bottomRGB 通过 bypass 路由。RMAN-22210",
      "ascii_letters": 55,
      "cjk_chars": 9
    },
    {
      "item_id": "30b2ede66f:547",
      "text": "移除了自 R24.0 起已经弃用并隐藏的 light/display/sample filter VOP nodes（VOP 节点）。RMAN-23220",
      "ascii_letters": 40,
      "cjk_chars": 15
    },
    {
      "item_id": "30b2ede66f:548",
      "text": "已将 \"density grid\" 添加到 Solaris Render Geometry Settings。RMAN-23252",
      "ascii_letters": 44,
      "cjk_chars": 5
    },
    {
      "item_id": "30b2ede66f:550",
      "text": "已将 .tex 和 .b2r 添加到 Houdini 可识别的 image file types（图像文件类型）中。在 Houdini 的 image file browser UI（图像文件浏览器 UI）中，.tex/.b2r 现在会列在 \"Show files matching\" 中，并且会被 \"Show sequences as one entry\" 针对 Frame Range/UDIM/UV Tile 正确处理（后两种情况仅适用于 Houdini 20.0.811 或 20.5.339 及之后版本）。在 RenderMan VOP nodes（节点）上，应对 texture file parameters（纹理文件参数）使用 \"image\" 类型，以受益于上述 UI 功能。RMAN-22639",
      "ascii_letters": 174,
      "cjk_chars": 82
    },
    {
      "item_id": "30b2ede66f:551",
      "text": "已将 denoiser tiles（降噪器分块）和 asymmetry denoiser（非对称降噪器）添加到 denoiser ROP。",
      "ascii_letters": 41,
      "cjk_chars": 17
    },
    {
      "item_id": "30b2ede66f:552",
      "text": "修复了 preset browser（预设浏览器）从 RfH/RfSolaris 向 RfM 传递 material（材质）的问题。RMAN-22527",
      "ascii_letters": 40,
      "cjk_chars": 17
    },
    {
      "item_id": "30b2ede66f:553",
      "text": "使用 Scene Import LOP 将 PxrDomeLight OBJ 转换为 USD 时，Domelights（圆顶灯）现在会带有 180 的 Y rotation（Y 轴旋转）。RMAN-23599",
      "ascii_letters": 56,
      "cjk_chars": 19
    },
    {
      "item_id": "30b2ede66f:554",
      "text": "PxrLightFilter、PxrDisplayFilter、PxrSampleFilter、PxrIntegrator LOPs 现已弃用，改为使用按 prim type（图元类型）划分的 LOPs。",
      "ascii_letters": 74,
      "cjk_chars": 16
    },
    {
      "item_id": "30b2ede66f:555",
      "text": "PxrBakeTexture 现在可以正确写入磁盘上已存在的 non tex files（非 tex 文件）。RMAN-22516",
      "ascii_letters": 32,
      "cjk_chars": 18
    },
    {
      "item_id": "30b2ede66f:556",
      "text": "已将 \"ri:attributes:user:maxtextureresolution\" 和 \"ri:attributes:user:texturemipbias\" 添加到 Render Geometry Settings LOP 的 RenderMan tab（标签页）。RMAN-23490",
      "ascii_letters": 107,
      "cjk_chars": 10
    },
    {
      "item_id": "30b2ede66f:557",
      "text": "PxrVolume shader 现在已连接到 Solaris/USD 中的 outputs:ri:volume terminal shader（终端着色器）。RMAN-23427",
      "ascii_letters": 58,
      "cjk_chars": 13
    },
    {
      "item_id": "30b2ede66f:558",
      "text": "RenderSettings 的默认值将 \"Bucket Order\" 设为 \"Circle\"，将 \"World Origin\" 设为 \"World\"，以匹配 schemas（模式）。RMAN-23070",
      "ascii_letters": 58,
      "cjk_chars": 15
    },
    {
      "item_id": "30b2ede66f:559",
      "text": "Solaris UI：将 ri:hider:invert 的默认值改为 1，使其与 PxrOptionsAPI USD schema 保持一致。",
      "ascii_letters": 44,
      "cjk_chars": 14
    },
    {
      "item_id": "30b2ede66f:560",
      "text": "hdPrman 现在可以渲染 Houdini COPs network images（COPs 网络图像）。只需在 filename string（文件名字符串）中放入 COPs network path（以 op: 前缀开头），也就是通常在 material network（材质网络）中放置 texture file（纹理文件）路径的位置，即可满足要求。RMAN-23476",
      "ascii_letters": 96,
      "cjk_chars": 55
    },
    {
      "item_id": "30b2ede66f:561",
      "text": "修复了 non .tex textures（非 .tex 纹理）无法与 primstr 配合工作的问题。RMAN-23485",
      "ascii_letters": 28,
      "cjk_chars": 16
    },
    {
      "item_id": "30b2ede66f:562",
      "text": "修复了 solo-ing（独显）mtlx node（mtlx 节点）无法工作的问题。RMAN-22851",
      "ascii_letters": 23,
      "cjk_chars": 14
    },
    {
      "item_id": "30b2ede66f:563",
      "text": "Solaris：从 preset browser（预设浏览器）正确导入 light rigs（灯光组）参数。RMAN-23268",
      "ascii_letters": 33,
      "cjk_chars": 15
    },
    {
      "item_id": "30b2ede66f:564",
      "text": "Husk renders（Husk 渲染）现在会输出 render time（渲染时间）和 memory usage stats（内存使用统计）。RMAN-23132",
      "ascii_letters": 45,
      "cjk_chars": 18
    },
    {
      "item_id": "30b2ede66f:565",
      "text": "扩展了 preset browser（预设浏览器）的能力，使其可作用于任意 LOP networks（LOP 网络），而不只是 root stage（根 stage）。RMAN-21813",
      "ascii_letters": 45,
      "cjk_chars": 26
    },
    {
      "item_id": "30b2ede66f:566",
      "text": "在 VOP 到 USD 的转换中已 bypass（旁路）null VOP nodes（空 VOP 节点）。RMAN-22184",
      "ascii_letters": 31,
      "cjk_chars": 12
    },
    {
      "item_id": "30b2ede66f:567",
      "text": "添加了新的 PxrStylizedLooks LOP node（LOP 节点）。RMAN-22081",
      "ascii_letters": 30,
      "cjk_chars": 7
    },
    {
      "item_id": "30b2ede66f:569",
      "text": "向 RfH Preferences dialog box（偏好设置对话框）添加了新的 \"XPU\" tab（标签页），其中为每个可用 GPU 提供 checkboxes（复选框）。RMAN-22348",
      "ascii_letters": 46,
      "cjk_chars": 28
    },
    {
      "item_id": "30b2ede66f:570",
      "text": "修复了各种 Pxr* LOP nodes（LOP 节点）上的 button callbacks（按钮回调）。\"Reset Control\" 现在只会重置单个 primitive（图元）上的 control parameters（控制参数）。\"Load Values From USD Primitive\" 现在会正确设置 ramp parameters（渐变参数）和 light filters' transform（灯光滤镜的变换）。RMAN-22637",
      "ascii_letters": 132,
      "cjk_chars": 48
    },
    {
      "item_id": "30b2ede66f:571",
      "text": "已从 RenderMan LOP 中移除 Ri:Shutter 参数。应改用 camera（相机）上的 Shutter settings（快门设置）。RMAN-22558",
      "ascii_letters": 46,
      "cjk_chars": 18
    },
    {
      "item_id": "30b2ede66f:572",
      "text": "修复了一个问题：如果同时在 viewport（视口）和 render gallery（渲染图库）中启动 RenderMan render（RenderMan 渲染），可能会发生崩溃。注意，同时运行 viewport 和 gallery render 不是受支持的配置，并且 gallery renders 仍可能失败。RMAN-21323",
      "ascii_letters": 84,
      "cjk_chars": 53
    },
    {
      "item_id": "30b2ede66f:573",
      "text": "修复了 RIS 中 mesh lights（网格灯）在带有 velocity/deformation blur（速度/变形模糊）时渲染不正确的问题。在 XPU 中，mesh lights 应能随所有 motion blur（运动模糊）正确渲染。RMAN-23314",
      "ascii_letters": 63,
      "cjk_chars": 40
    },
    {
      "item_id": "30b2ede66f:577",
      "text": "RenderMan Render Settings LOP 已重写，包括使用新的 RenderMan Render Vars node（节点）、能够设置每个 primitive path（图元路径），并将 integrator（积分器）作为单独的 primitive（图元）。RMAN-23116",
      "ascii_letters": 85,
      "cjk_chars": 33
    },
    {
      "item_id": "30b2ede66f:578",
      "text": "PxrMeshLight 和 PxrVolumeLight LOPs 已弃用，H21 中改用 Geometry Light LOP。",
      "ascii_letters": 47,
      "cjk_chars": 7
    },
    {
      "item_id": "30b2ede66f:579",
      "text": "hdPrman 中的 Progress（进度）现在可在 Solaris 中用于 XPU。RMAN-22667",
      "ascii_letters": 29,
      "cjk_chars": 11
    },
    {
      "item_id": "30b2ede66f:580",
      "text": "Solaris：修复了 vdb grids（VDB 网格）以 float3 输出时可能发生的崩溃；现在默认输出为 vector。RMAN-23870",
      "ascii_letters": 33,
      "cjk_chars": 23
    },
    {
      "item_id": "30b2ede66f:581",
      "text": "修复了一个错误：在 Windows 上使用 XPU 时，Houdini VDB renders（VDB 渲染）有时会失败。RMAN-22697",
      "ascii_letters": 34,
      "cjk_chars": 19
    },
    {
      "item_id": "30b2ede66f:582",
      "text": "修复了 occluded、unoccluded 和 shadow AOVs 的 LPE，使其可在 Solaris 中用于 holdouts（遮挡保留对象）。RMAN-22603",
      "ascii_letters": 50,
      "cjk_chars": 18
    },
    {
      "item_id": "30b2ede66f:583",
      "text": "修复了在使用 Solaris 时会阻止 preset（预设）导出到 preset browser（预设浏览器）的错误。RMAN-23685、RMAN-23871",
      "ascii_letters": 34,
      "cjk_chars": 23
    },
    {
      "item_id": "30b2ede66f:584",
      "text": "interactive denoiser（交互式降噪器）现在可在 RfH Classic 中使用。",
      "ascii_letters": 29,
      "cjk_chars": 13
    },
    {
      "item_id": "30b2ede66f:585",
      "text": "Solaris：已为尚未预转换为 prman tex files（prman tex 文件）、因此由 RtxHioImage plug-in（插件）处理的 texture file names（纹理文件名）添加对 <UDIM> tag（标签）的支持。注意，不推荐使用此 workflow（工作流）。渲染时，预先将 udim textures（udim 纹理）转换为 tex 会获得更好的性能。",
      "ascii_letters": 95,
      "cjk_chars": 61
    },
    {
      "item_id": "30b2ede66f:586",
      "text": "Solaris：已修正 PxrSphereCamera Vertical Sweep 的默认值，使其匹配 PxrSphereCamera.args 中的 ''180'' 默认值。",
      "ascii_letters": 54,
      "cjk_chars": 16
    },
    {
      "item_id": "30b2ede66f:587",
      "text": "修复了在 Solaris 中编辑 RIS integrator（积分器）时发生的崩溃。RMAN-23401",
      "ascii_letters": 24,
      "cjk_chars": 16
    },
    {
      "item_id": "30b2ede66f:588",
      "text": "Gobo 和 Blocker Light filters（灯光滤镜）现已弃用。请改用 Cookie 和 Rod filters。",
      "ascii_letters": 39,
      "cjk_chars": 13
    },
    {
      "item_id": "30b2ede66f:589",
      "text": "RfSolaris：修复了 Solaris Render Gallery 中的 render regions（渲染区域）。RMAN-23768",
      "ascii_letters": 46,
      "cjk_chars": 9
    },
    {
      "item_id": "30b2ede66f:590",
      "text": "向 Solaris 中 barn 和 cookie light filters（灯光滤镜）的 guide geometry（引导几何体）添加 directional arrow（方向箭头）。",
      "ascii_letters": 58,
      "cjk_chars": 19
    },
    {
      "item_id": "30b2ede66f:591",
      "text": "HdPrmanLoaderRendererPlugin_Global.ds 现在会自动从 USD schemas 生成。这个新的 HdPrmanLoaderRendererPlugin_Global.ds 由 RenderMan Render Settings LOP 使用。在 Houdini 21 中，我们会公开 relationship parameters（关系参数），用于附加 integrator（积分器）以及 display/sample filters（显示/采样过滤器），作为 PxrAssign LOP 的替代方案。RMAN-23106",
      "ascii_letters": 181,
      "cjk_chars": 49
    },
    {
      "item_id": "30b2ede66f:592",
      "text": "RfHoudini：添加了 menu script（菜单脚本），用于将 <udim> 转换为 <UDIM> tokens（token），因为现在仅支持大写的 UDIM。RMAN-23942",
      "ascii_letters": 46,
      "cjk_chars": 23
    }
  ],
  "required_phrase_missing": [],
  "section_order_positions": [],
  "section_order_ok": true,
  "passed": true
}