{
  "phase": 680,
  "file": "RU/657228237-RazorBack Rendering.html",
  "file_id": "fdb83dacb3",
  "source_items": 10,
  "translation_rows": 10,
  "source_items_match_translation_rows": true,
  "duplicate_rows": [],
  "missing_item_ids": [],
  "extra_item_ids": [],
  "tag_fingerprint_identical": true,
  "rendered_markup_matches_target_markup": true,
  "glossary_violations": [],
  "direct_placement_missing": [],
  "actionable_long_source_residuals": [],
  "accepted_long_source_residuals": [],
  "actionable_ascii_heavy_residuals": [],
  "accepted_ascii_heavy_residuals": [
    {
      "item_id": "fdb83dacb3:0",
      "text": "RazorBack 项目的渲染与输出设置（Rendering）",
      "ascii_letters": 18,
      "cjk_chars": 10
    },
    {
      "item_id": "fdb83dacb3:1",
      "text": "设置 render layers 和 AOVs 时，关键是为每个 main light 输出一个 Light Path Expression（LPE）。也可以把功能相似的 lights 组合在一起，例如 rim lights。",
      "ascii_letters": 62,
      "cjk_chars": 30
    },
    {
      "item_id": "fdb83dacb3:3",
      "text": "此外，将 diffusers 与 speculars 分离，可以 fine-tune 并修正 shading 和 lighting 之间的任何 discrepancies。",
      "ascii_letters": 54,
      "cjk_chars": 17
    },
    {
      "item_id": "fdb83dacb3:5",
      "text": "这样可以在 post-production 中进行有针对性的 adjustments，缓解问题并获得期望的 visual outcomes。",
      "ascii_letters": 39,
      "cjk_chars": 23
    },
    {
      "item_id": "fdb83dacb3:6",
      "text": "为了简化 denoising process 并方便 mask creation，建议将 beauty pass 与 Light Path Expressions（LPEs）和 utilities 分离。",
      "ascii_letters": 71,
      "cjk_chars": 14
    },
    {
      "item_id": "fdb83dacb3:7",
      "text": "这种 separation 让每个 AOV 都更容易单独 denoise。此外，按 material 或 object 提取 cryptomatte 可以快速创建 masks；即使 assets 在运动，masks 也会保持一致。",
      "ascii_letters": 61,
      "cjk_chars": 34
    },
    {
      "item_id": "fdb83dacb3:8",
      "text": "通过将 beauty pass 与 LPEs 和 utilities 分离，denoising 会更高效，因为每个 component 都可以独立处理。",
      "ascii_letters": 41,
      "cjk_chars": 22
    },
    {
      "item_id": "fdb83dacb3:9",
      "text": "此外，使用 Cryptomatte 创建 masks 提供了极高的灵活性，可以对 scene 内的 elements 进行精确控制，不受 asset movement 影响。这种方法提升了整体 post-production workflow，让 final renders 更顺畅、更精确。",
      "ascii_letters": 76,
      "cjk_chars": 46
    }
  ],
  "required_phrase_missing": [],
  "section_order_positions": [
    {
      "pattern": "RazorBack 项目的渲染与输出设置",
      "position": 1932
    },
    {
      "pattern": "render layers",
      "position": 1974
    },
    {
      "pattern": "Light Path Expression",
      "position": 2020
    },
    {
      "pattern": "compositing",
      "position": 2113
    },
    {
      "pattern": "diffusers",
      "position": 2144
    },
    {
      "pattern": "beauty pass",
      "position": 3310
    },
    {
      "pattern": "cryptomatte",
      "position": 3438
    },
    {
      "pattern": "Cryptomatte",
      "position": 3587
    }
  ],
  "section_order_ok": true,
  "passed": true
}