{
  "phase": 453,
  "source_relative": "RFK27/546179420-Using PxrVary.html",
  "file_id": "1eb952b925",
  "source_items": 14,
  "jsonl_rows": 14,
  "precheck_report": "renderman-docs-27/phases/phase-453-precheck-report.json",
  "apply_report": "renderman-docs-27/phases/phase-453-apply-report.json",
  "apply_layout_errors": [],
  "apply_glossary_violations": [],
  "tag_fingerprint_identical": true,
  "rendered_matches_target": true,
  "duplicate_item_ids": [],
  "missing_item_ids": [],
  "extra_item_ids": [],
  "json_errors": [],
  "glossary_violations": [],
  "direct_html_placement_missing": [],
  "actionable_long_source_residuals": [],
  "accepted_long_source_residuals": [
    {
      "item_id": "1eb952b925:0",
      "source": "PxrVary Example",
      "translation": "PxrVary Example（PxrVary 示例）"
    },
    {
      "item_id": "1eb952b925:8",
      "source": "Katana documentation",
      "translation": "Katana documentation"
    },
    {
      "item_id": "1eb952b925:13",
      "source": "PxrVary Katana 2.6v4 scene",
      "translation": "PxrVary Katana 2.6v4 scene"
    }
  ],
  "actionable_ascii_heavy_residuals": [],
  "accepted_ascii_heavy_residuals_count": 11,
  "missing_required_phrases": [],
  "missing_required_sequences": [],
  "sequence_checked": [
    "PxrVary Example（PxrVary 示例）",
    "shader attributes",
    "PxrVary",
    "就派上用场",
    "Katana example file",
    "Identifier ID",
    "Attribute selections",
    "Katana documentation",
    "example OpScript",
    "Interface.SetAttr",
    "primitive create",
    "四个不同 outputs",
    "PxrVary Katana 2.6v4 scene"
  ],
  "status": "pass"
}