{
  "phase": 693,
  "file": "RU/657555620-RazorBack Procedural Texturing.html",
  "file_id": "4ca71764a4",
  "source_items": 7,
  "translation_rows": 7,
  "source_items_match_translation_rows": true,
  "duplicate_rows": [],
  "missing_item_ids": [],
  "extra_item_ids": [],
  "tag_fingerprint_identical": true,
  "rendered_markup_matches_target_markup": true,
  "glossary_violations": [],
  "direct_placement_missing": [],
  "actionable_long_source_residuals": [],
  "accepted_long_source_residuals": [
    {
      "item_id": "4ca71764a4:0",
      "source": "Texturing Procedural"
    }
  ],
  "actionable_ascii_heavy_residuals": [],
  "accepted_ascii_heavy_residuals": [
    {
      "item_id": "4ca71764a4:0",
      "text": "RazorBack 程序化贴图流程（Texturing Procedural）",
      "ascii_letters": 28,
      "cjk_chars": 7
    },
    {
      "item_id": "4ca71764a4:1",
      "text": "为了引入最大 variation，将 ISO maps 和 displacement/utility maps 与 rock、granite maps 结合，并使用 triplanar projection，是非常关键的。",
      "ascii_letters": 73,
      "cjk_chars": 20
    },
    {
      "item_id": "4ca71764a4:2",
      "text": "这种 approach 显著增强 detail，并让 Mari node 内创建的 layers 之间能够平滑 transition。",
      "ascii_letters": 38,
      "cjk_chars": 18
    },
    {
      "item_id": "4ca71764a4:3",
      "text": "在 combining scanned map projection 和 procedural nodes 的 procedural pass 之后，会进行 final texturing pass，以加入大量 micro-detail variations。",
      "ascii_letters": 97,
      "cjk_chars": 13
    },
    {
      "item_id": "4ca71764a4:4",
      "text": "Substance Designer 和 Substance Painter 用于调制 scales 上的 HSV variations，并引入 dead skin 的 subtle details，这些 details 会策略性地放置在 scales 的特定末端。",
      "ascii_letters": 86,
      "cjk_chars": 26
    },
    {
      "item_id": "4ca71764a4:5",
      "text": "在整个过程中，会考虑 creature 的 movement 和 environment，并参考 texturing materials 来辅助 decision。",
      "ascii_letters": 53,
      "cjk_chars": 17
    },
    {
      "item_id": "4ca71764a4:6",
      "text": "最后一步是增强 scales edges 上特定的 specular highlights，同时增加 albedo detail。mask creation 完成后，重点会回到 Mari 进行 texture publishing，标志着进入 Lookdev stage。",
      "ascii_letters": 86,
      "cjk_chars": 30
    }
  ],
  "required_phrase_missing": [],
  "section_order_positions": [
    {
      "pattern": "RazorBack 程序化贴图流程",
      "position": 1996
    },
    {
      "pattern": "ISO maps",
      "position": 2062
    },
    {
      "pattern": "triplanar projection",
      "position": 2126
    },
    {
      "pattern": "procedural pass",
      "position": 3178
    },
    {
      "pattern": "Substance Designer",
      "position": 3260
    },
    {
      "pattern": "specular highlights",
      "position": 4386
    },
    {
      "pattern": "Lookdev",
      "position": 4482
    }
  ],
  "section_order_ok": true,
  "passed": true
}